ntac/__init__.py
ntac/data.py
ntac/graph_data.py
ntac/visualizer.py
ntac/seeded/__init__.py
ntac/seeded/seeded.py
ntac/unseeded/__init__.py
ntac/unseeded/convert.py
ntac/unseeded/problem.py
ntac/unseeded/seeded.py
ntac/unseeded/unseeded.py
ntac/unseeded/util.py
ntac/unseeded/utilgpu.py
ntac-0.1.1.dist-info/METADATA
ntac-0.1.1.dist-info/WHEEL
ntac-0.1.1.dist-info/entry_points.txt
ntac-0.1.1.dist-info/licenses/LICENSE
ntac-0.1.1.dist-info/RECORD
