Metadata-Version: 2.4
Name: ntac
Version: 0.1.1
Summary: Add your description here
Author-email: Ben Jourdan <ben@jourdan.me>, Gregory Schwartzman <gregory.schwartzman@gmail.com>, David García Soriano <elhipercubo@gmail.com>, Arie Matsliah <arie.matsliah@gmail.com>
License-File: LICENSE
Requires-Python: >=3.10
Requires-Dist: bottleneck>=1.5.0
Requires-Dist: matplotlib>=3.10.3
Requires-Dist: numba>=0.61.0
Requires-Dist: pandas>=2.2.3
Requires-Dist: scikit-learn>=1.6.1
Requires-Dist: scipy>=1.15.2
Requires-Dist: tqdm>=4.67.1
Provides-Extra: dev
Requires-Dist: black; extra == 'dev'
Requires-Dist: build; extra == 'dev'
Requires-Dist: furo; extra == 'dev'
Requires-Dist: pytest; extra == 'dev'
Requires-Dist: ruff; extra == 'dev'
Requires-Dist: sphinx; extra == 'dev'
Requires-Dist: twine; extra == 'dev'
Provides-Extra: gpu
Requires-Dist: cuda-python>=12.9.0; extra == 'gpu'
Requires-Dist: cupy-cuda12x>=13.4.1; extra == 'gpu'
